{"0": {"Cluster": 0, "Places": ["Transportation", "Shop", "Other rooms", "Beach"], "Activities": ["Public Transport", "Shopping", "Walking outdoor", "Walking indoor", "Meeting", "Resting"], "Objects": ["person", "cell phone", "chair", "laptop", "backpack", "book", "cup", "dining table", "tvmonitor", "refrigerator"]}, "1": {"Cluster": 1, "Places": ["Other rooms", "Transportation"], "Activities": ["Mobile", "Walking indoor", "Walking outdoor", "Shopping"], "Objects": ["person", "cell phone", "chair", "laptop", "bottle", "cup", "tvmonitor", "train", "keyboard", "car"]}}