{"0": {"Cluster": 0, "Places": ["Office", "Transportation"], "Activities": ["Working", "Driving", "Walking outdoor", "Socializing"], "Objects": ["tvmonitor", "keyboard", "person", "laptop", "cup", "chair", "bottle", "dining table", "fork"]}, "1": {"Cluster": 1, "Places": ["Office"], "Activities": ["Working", "Mobile", "Walking outdoor", "Shopping"], "Objects": ["tvmonitor", "person", "keyboard", "cup", "laptop", "chair", "bottle", "mouse"]}, "2": {"Cluster": 2, "Places": ["Office"], "Activities": ["Working", "Mobile", "Talking", "Walking outdoor", "Shopping"], "Objects": ["tvmonitor", "person", "laptop", "keyboard", "cup", "chair", "book", "mouse"]}, "3": {"Cluster": 3, "Places": ["Office"], "Activities": ["Working", "Mobile", "Shopping"], "Objects": ["tvmonitor", "keyboard", "laptop", "person", "mouse", "bottle", "sink", "chair", "cup"]}, "4": {"Cluster": 4, "Places": ["Office", "Transportation"], "Activities": ["Shopping", "Talking", "Mobile", "Working"], "Objects": ["person", "dining table", "wine glass", "bowl", "chair", "cup", "fork", "keyboard", "tvmonitor", "laptop"]}, "5": {"Cluster": 5, "Places": ["Transportation", "Mountains, hills, desert, sky"], "Activities": ["Mobile", "Walking outdoor", "Shopping", "Walking indoor", "Public Transport"], "Objects": ["person", "tvmonitor", "laptop", "cup", "keyboard", "donut", "cell phone"]}, "6": {"Cluster": 6, "Places": ["Office"], "Activities": ["Mobile", "Shopping", "Walking indoor", "Meeting", "Walking outdoor", "Working", "Socializing"], "Objects": ["person", "chair", "tvmonitor", "laptop", "keyboard", "cup", "dining table", "cell phone"]}}